psqlc/__init__.py
psqlc/__version__.py
psqlc/psqlc.cp311-win_amd64.pyd
psqlc-1.1.21.dist-info/licenses/LICENSE
psqlc-1.1.21.dist-info/METADATA
psqlc-1.1.21.dist-info/WHEEL
psqlc-1.1.21.dist-info/entry_points.txt
psqlc-1.1.21.dist-info/top_level.txt
psqlc-1.1.21.dist-info/RECORD
