Metadata-Version: 2.4
Name: psqlc
Version: 1.1.21
Summary: Feature-rich command-line interface tool for managing PostgreSQL databases. Built with `asyncpg` and featuring beautiful output formatting with Rich, it provides intelligent auto-detection of database configurations from Django settings, environment files, and various configuration formats.
Home-page: https://github.com/cumulus13/psqlc
Author: cumulus13
Author-email: cumulus13 <cumulus13@gmail.com>
License-Expression: MIT
Project-URL: Bug Reports, https://github.com/cumulus13/psqlc/issues
Project-URL: Source, https://github.com/cumulus13/psqlc
Project-URL: Documentation, https://psqlc.readthedocs.io
Keywords: postgresql,automation,analytics,developer tools,monitoring,devops,django,asyncpg,dotenv
Classifier: Development Status :: 5 - Production/Stable
Classifier: Intended Audience :: Developers
Classifier: Topic :: Software Development :: Build Tools
Classifier: Topic :: System :: Filesystems
Classifier: Programming Language :: Python :: 3
Classifier: Programming Language :: Python :: 3.6
Classifier: Programming Language :: Python :: 3.7
Classifier: Programming Language :: Python :: 3.8
Classifier: Programming Language :: Python :: 3.9
Classifier: Programming Language :: Python :: 3.10
Classifier: Programming Language :: Python :: 3.11
Classifier: Operating System :: OS Independent
Classifier: Environment :: Console
Requires-Python: >=3.6
License-File: LICENSE
Requires-Dist: rich
Requires-Dist: asyncpg
Requires-Dist: licface
Requires-Dist: envdot
Requires-Dist: pwinput
Requires-Dist: richcolorlog
Provides-Extra: dev
Requires-Dist: cython; extra == "dev"
Dynamic: author
Dynamic: home-page
Dynamic: license-file
Dynamic: requires-python
